README.md
setup.py
pyautodoc/__init__.py
pyautodoc.egg-info/PKG-INFO
pyautodoc.egg-info/SOURCES.txt
pyautodoc.egg-info/dependency_links.txt
pyautodoc.egg-info/entry_points.txt
pyautodoc.egg-info/requires.txt
pyautodoc.egg-info/top_level.txt
pyautodoc/generators/__init__.py
pyautodoc/generators/makefiles.py
pyautodoc/generators/rst_file.py
pyautodoc/generators/sphinx_config_file.py
pyautodoc/generators/sphinx_structure.py
pyautodoc/i18n/__init__.py
pyautodoc/i18n/dictionary.py
pyautodoc/i18n/exceptions.py
pyautodoc/i18n/locales/__init__.py
pyautodoc/i18n/locales/en.py
pyautodoc/i18n/locales/es.py
pyautodoc/identify/__init__.py
pyautodoc/identify/data.py
pyautodoc/identify/packages.py
pyautodoc/identify/project_structure.py
pyautodoc/scripts/__init__.py
pyautodoc/scripts/main.py
pyautodoc/utils/__init__.py
pyautodoc/utils/path.py
pyautodoc/utils/stringify.py