Metadata-Version: 2.1
Name: pyautodoc
Version: 0.6.3
Summary: UNKNOWN
Home-page: https://github.com/alvarogf97/pyautodoc
Author: Alvaro
Author-email: alvarogf97@gmail.com
License: MIT
Platform: UNKNOWN
Requires-Python: >=3.4
